python_amazon_sp_api-1.9.60.data/scripts/make_endpoint
python_amazon_sp_api-1.9.60.dist-info/licenses/LICENSE
sp_api/__init__.py
sp_api/__version__.py
sp_api/api/__init__.py
sp_api/api/amazon_warehousing_and_distribu/__init__.py
sp_api/api/amazon_warehousing_and_distribu/amazon_warehousing_and_distribu.py
sp_api/api/aplus_content/__init__.py
sp_api/api/aplus_content/aplus_content.py
sp_api/api/application_integrations/__init__.py
sp_api/api/application_integrations/application_integrations.py
sp_api/api/application_management/__init__.py
sp_api/api/application_management/application_management.py
sp_api/api/authorization/__init__.py
sp_api/api/authorization/authorization.py
sp_api/api/catalog/__init__.py
sp_api/api/catalog/catalog.py
sp_api/api/catalog_items/__init__.py
sp_api/api/catalog_items/catalog_items.py
sp_api/api/customer_feedback/__init__.py
sp_api/api/customer_feedback/customer_feedback.py
sp_api/api/data_kiosk/__init__.py
sp_api/api/data_kiosk/data_kiosk.py
sp_api/api/easy_ship/__init__.py
sp_api/api/easy_ship/easy_ship.py
sp_api/api/external_fulfillment/__init__.py
sp_api/api/external_fulfillment/external_fulfillment.py
sp_api/api/fba_inbound_eligibility/__init__.py
sp_api/api/fba_inbound_eligibility/fba_inbound_eligibility.py
sp_api/api/fba_small_and_light/__init__.py
sp_api/api/fba_small_and_light/fba_small_and_light.py
sp_api/api/feeds/__init__.py
sp_api/api/feeds/feeds.py
sp_api/api/finances/__init__.py
sp_api/api/finances/finances.py
sp_api/api/fulfillment_inbound/__init__.py
sp_api/api/fulfillment_inbound/fulfillment_inbound.py
sp_api/api/fulfillment_outbound/__init__.py
sp_api/api/fulfillment_outbound/fulfillment_outbound.py
sp_api/api/inventories/__init__.py
sp_api/api/inventories/inventories.py
sp_api/api/listings_items/__init__.py
sp_api/api/listings_items/listings_items.py
sp_api/api/listings_restrictions/__init__.py
sp_api/api/listings_restrictions/listings_restrictions.py
sp_api/api/merchant_fulfillment/__init__.py
sp_api/api/merchant_fulfillment/merchant_fulfillment.py
python_amazon_sp_api-1.9.60.dist-info/METADATA
python_amazon_sp_api-1.9.60.dist-info/WHEEL
python_amazon_sp_api-1.9.60.dist-info/top_level.txt
python_amazon_sp_api-1.9.60.dist-info/RECORD
