Metadata-Version: 2.4
Name: python-amazon-sp-api
Version: 1.9.60
Summary: Python wrapper for the Amazon Selling-Partner API
Home-page: https://github.com/saleweaver/python-amazon-sp-api
Author: Michael Primke
Author-email: primke.michael@gmail.com
License: MIT
License-File: LICENSE
Requires-Dist: requests>=2.32.1
Requires-Dist: cachetools>=4.2
Requires-Dist: confuse>=1.4
Provides-Extra: aws-caching
Requires-Dist: aws-secretsmanager-caching; extra == "aws-caching"
Requires-Dist: boto3; extra == "aws-caching"
Provides-Extra: aws
Requires-Dist: boto3; extra == "aws"
Dynamic: author
Dynamic: author-email
Dynamic: home-page
Dynamic: license
Dynamic: license-file
Dynamic: provides-extra
Dynamic: requires-dist
Dynamic: summary
